hufengguo/__init__.py
hufengguo/filepath.py
hufengguo/filepathwindow.py
hufengguo/hanzidigit.py
hufengguo/hufengguo.py
hufengguo/pdf.py
hufengguo-1.3.3.dist-info/METADATA
hufengguo-1.3.3.dist-info/WHEEL
hufengguo-1.3.3.dist-info/top_level.txt
hufengguo-1.3.3.dist-info/RECORD
