Metadata-Version: 2.1
Name: hufengguo
Version: 1.3.3
Summary: A small example package from Hufengguo, CUC
Author-email: cucialhu <cuchufengguo@163.com>
Classifier: Programming Language :: Python :: 3
Classifier: License :: OSI Approved :: MIT License
Classifier: Operating System :: OS Independent
Requires-Python: >=3.6
Requires-Dist: jieba >=0.42.1
Requires-Dist: chardet <5.0.0 ; python_version == "3.6"
Requires-Dist: chardet >=5.0.0 ; python_version > "3.6"
Provides-Extra: all
Requires-Dist: hufengguo[pdf] ; extra == 'all'
Provides-Extra: pdf
Requires-Dist: pypdf <=4.3.1 ; (python_version <= "3.7") and extra == 'pdf'
Requires-Dist: pymupdf <=1.19.3 ; (python_version == "3.6") and extra == 'pdf'
Requires-Dist: pypdf >4.3.1 ; (python_version > "3.7") and extra == 'pdf'
Requires-Dist: pymupdf >1.19.3 ; (python_version >= "3.7") and extra == 'pdf'
